logsteplib/__init__.py
logsteplib/__main__.py
logsteplib/stream.py
logsteplib-0.0.22.dist-info/licenses/LICENSE
logsteplib-0.0.22.dist-info/METADATA
logsteplib-0.0.22.dist-info/WHEEL
logsteplib-0.0.22.dist-info/top_level.txt
logsteplib-0.0.22.dist-info/RECORD
